py211mm/initialcond.py
py211mm/models.py
py211mm/readio.py
py211mm/__init__.py
py211mm-0.0.1.dist-info/DESCRIPTION.rst
py211mm-0.0.1.dist-info/METADATA
py211mm-0.0.1.dist-info/metadata.json
py211mm-0.0.1.dist-info/RECORD
py211mm-0.0.1.dist-info/top_level.txt
py211mm-0.0.1.dist-info/WHEEL
