Metadata-Version: 2.0
Name: py211mm
Version: 0.0.1
Summary: Tool for generating mock catalogs for 21cm experiments.
Home-page: https://bitbucket.org/kaurov/211mm
Author: Alexander A Kaurov
Author-email: akaurov@gmail.com
License: MIT
Keywords: astronomy astrophysics 21cm reionization
Platform: UNKNOWN
Classifier: Development Status :: 3 - Alpha
Classifier: Intended Audience :: Science/Research
Classifier: Topic :: Scientific/Engineering :: Astronomy
Classifier: Programming Language :: Python :: 2.7
Requires-Dist: numpy (>=1.7)
Requires-Dist: cosmolopy
